LICENSE
MANIFEST.in
README.rst
setup.py
mwcites/__init__.py
mwcites/identifier.py
mwcites/mwcites.py
mwcites.egg-info/PKG-INFO
mwcites.egg-info/SOURCES.txt
mwcites.egg-info/dependency_links.txt
mwcites.egg-info/entry_points.txt
mwcites.egg-info/requires.txt
mwcites.egg-info/top_level.txt
mwcites/extractors/__init__.py
mwcites/extractors/arxiv.py
mwcites/extractors/doi.py
mwcites/extractors/isbn.py
mwcites/extractors/pubmed.py
mwcites/extractors/tests/__init__.py
mwcites/extractors/tests/test_arxiv.py
mwcites/extractors/tests/test_doi.py
mwcites/extractors/tests/test_isbn.py
mwcites/extractors/tests/test_pubmed.py
mwcites/utilities/__init__.py
mwcites/utilities/extract.py
mwcites/utilities/tests/__init__.py
mwcites/utilities/tests/test_extract.py