Metadata-Version: 1.1
Name: mwcites
Version: 0.2.0
Summary: A collection of scripts and utilities for extracting citations to academic literature from Wikipedia's XML database dumps.
Home-page: https://github.com/halfak/Extract-scholarly-article-citations-from-Wikipedia
Author: Aaron Halfaker
Author-email: ahalfaker@wikimedia.org
License: MIT
Platform: UNKNOWN
Classifier: Programming Language :: Python :: 3
Classifier: Development Status :: 3 - Alpha
Classifier: License :: OSI Approved :: MIT License
Classifier: Intended Audience :: Science/Research
Classifier: Intended Audience :: System Administrators
Classifier: Intended Audience :: Developers
Classifier: Operating System :: OS Independent
Classifier: Topic :: Utilities
Classifier: Topic :: Scientific/Engineering
